autorunrecord-0.4-py3.7-nspkg.pth
sphinxcontrib/autorunrecord.py
sphinxcontrib/pycon.py
autorunrecord-0.4.dist-info/METADATA
autorunrecord-0.4.dist-info/WHEEL
autorunrecord-0.4.dist-info/namespace_packages.txt
autorunrecord-0.4.dist-info/top_level.txt
autorunrecord-0.4.dist-info/RECORD
