Metadata-Version: 2.1
Name: autorunrecord
Version: 0.4
Summary: Sphinx extension autorunrecord
Home-page: http://github.com/mih/autorunrecord
Author: Michael Hanke
Author-email: michael.hanke@gmail.com
License: BSD
Platform: any
Classifier: Development Status :: 4 - Beta
Classifier: Environment :: Console
Classifier: Environment :: Web Environment
Classifier: Intended Audience :: Developers
Classifier: License :: OSI Approved :: BSD License
Classifier: Operating System :: OS Independent
Classifier: Programming Language :: Python
Classifier: Topic :: Documentation
Classifier: Topic :: Utilities
Requires-Dist: Sphinx
